[
  {
    "header": "21 декабря 1913",
    "text": "Считается, что в этот день в газете «New York World» был опубликован первый в мире современный кроссворд. Составителя звали Артур Уинн. Впрочем, надо сказать, что похожие головоломки существовали и ранее.",
    "type": "event"
  },
  {
    "header": "21 декабря 1957",
    "text": "Родился Сергей Алексеевич Мызников, российский лингвист.",
    "tag": "Q28499947",
    "type": "birth"
  },
  {
    "header": "21 декабря 1999",
    "text": "В Латвии принят Закон о языках, который официально регулировал использование и поддержку латышского языка, а также отметил статус латышского жестового языка, как основного средства коммуникации людей с нарушениями слуха.",
    "type": "event"
  }
]